lazer/__init__.py
lazer-0.1.10.dist-info/LICENSE
lazer-0.1.10.dist-info/METADATA
lazer-0.1.10.dist-info/WHEEL
lazer-0.1.10.dist-info/RECORD
